tstools/__init__.py
tstools/moments.py
tstools/vis.py
tstools-0.1.dist-info/METADATA
tstools-0.1.dist-info/WHEEL
tstools-0.1.dist-info/top_level.txt
tstools-0.1.dist-info/RECORD
